pyndl/__init__.py
pyndl/activation.py
pyndl/corpus.py
pyndl/correlation.py
pyndl/correlation_openmp.pyx
pyndl/count.py
pyndl/error_codes.pxd
pyndl/io.py
pyndl/ndl.py
pyndl/ndl_openmp.pyx
pyndl/ndl_parallel.cp38-win_amd64.pyd
pyndl/ndl_parallel.pxd
pyndl/ndl_parallel.pyx
pyndl/preprocess.py
pyndl/wh.py
pyndl-1.2.0.dist-info/LICENSE
pyndl-1.2.0.dist-info/WHEEL
pyndl-1.2.0.dist-info/METADATA
pyndl-1.2.0.dist-info/RECORD
