Metadata-Version: 2.1
Name: pyndl
Version: 1.2.0
Summary: Naive discriminative learning implements learning and classification models based on the Rescorla-Wagner equations.
Home-page: https://pyndl.readthedocs.io/en/latest/
License: MIT
Author: Konstantin Sering
Author-email: konstantin.sering@uni-tuebingen.de
Requires-Python: >=3.8,<3.12
Classifier: Development Status :: 5 - Production/Stable
Classifier: Environment :: Console
Classifier: Intended Audience :: Science/Research
Classifier: License :: OSI Approved :: MIT License
Classifier: Operating System :: MacOS
Classifier: Operating System :: Microsoft :: Windows
Classifier: Operating System :: POSIX :: Linux
Classifier: Programming Language :: Python :: 3
Classifier: Programming Language :: Python :: 3.8
Classifier: Programming Language :: Python :: 3.9
Classifier: Programming Language :: Python :: 3.10
Classifier: Topic :: Scientific/Engineering
Classifier: Topic :: Scientific/Engineering :: Artificial Intelligence
Classifier: Topic :: Scientific/Engineering :: Information Analysis
Requires-Dist: Cython (>=3.0.0,<4.0.0)
Requires-Dist: netCDF4 (>=1.6.0,<2.0.0)
Requires-Dist: numpy (>=1.23.1,<2.0.0)
Requires-Dist: pandas (>=1.4.3,<2.0.0)
Requires-Dist: scipy (>=1.9.0,<2.0.0)
Requires-Dist: xarray (>=2022.6.0,<2023.0.0)
Project-URL: Repository, https://github.com/quantling/pyndl
